oidcutils/__init__.py
oidcutils/client.py
gcp_oidc-0.0.12.dist-info/LICENSE
gcp_oidc-0.0.12.dist-info/METADATA
gcp_oidc-0.0.12.dist-info/WHEEL
gcp_oidc-0.0.12.dist-info/top_level.txt
gcp_oidc-0.0.12.dist-info/RECORD
