Metadata-Version: 2.1
Name: gcp-oidc
Version: 0.0.12
Summary: Generate OIDC tokens for GCP Service accounts.
Home-page: UNKNOWN
Author: Total Wine
Author-email: crsintegrations@totalwine.com
License: UNKNOWN
Platform: UNKNOWN
Classifier: Programming Language :: Python :: 3
Classifier: License :: OSI Approved :: MIT License
Classifier: Operating System :: OS Independent
Requires-Python: >=3.6
Requires-Dist: google-cloud-iam
